spiref/GLI-2012.xlsx
spiref/__init__.py
spiref/gli12.py
spiref/nhanes3.py
spiref-1.0.4.dist-info/LICENSE
spiref-1.0.4.dist-info/METADATA
spiref-1.0.4.dist-info/WHEEL
spiref-1.0.4.dist-info/top_level.txt
spiref-1.0.4.dist-info/RECORD
