Metadata-Version: 2.1
Name: spiref
Version: 1.0.4
Summary: This package contains the reference value calculator for spirometry.
Home-page: https://github.com/kennethv93/spiref
Author: Kenneth Verstraete
Author-email: verstraetekenneth@gmail.com
License: UNKNOWN
Platform: UNKNOWN
Classifier: Programming Language :: Python :: 3
Classifier: License :: OSI Approved :: MIT License
Classifier: Operating System :: OS Independent
Requires-Python: >=3.6
Requires-Dist: openpyxl
Requires-Dist: numpy
